canokit/__init__.py
canokit/core/__init__.py
canokit/core/fido.py
canokit/core/otp.py
canokit/core/smartcard.py
canokit/hsmauth.py
canokit/logging.py
canokit/management.py
canokit/oath.py
canokit/openpgp.py
canokit/piv.py
canokit/py.typed
canokit/support.py
canokit/yubiotp.py
ckman/__init__.py
ckman/_cli/__init__.py
ckman/_cli/__main__.py
ckman/_cli/aliases.py
ckman/_cli/apdu.py
ckman/_cli/config.py
ckman/_cli/fido.py
ckman/_cli/hsmauth.py
ckman/_cli/info.py
ckman/_cli/oath.py
ckman/_cli/openpgp.py
ckman/_cli/otp.py
ckman/_cli/piv.py
ckman/_cli/script.py
ckman/_cli/util.py
ckman/base.py
ckman/device.py
ckman/diagnostics.py
ckman/fido.py
ckman/hid/__init__.py
ckman/hid/base.py
ckman/hid/freebsd.py
ckman/hid/linux.py
ckman/hid/macos.py
ckman/hid/windows.py
ckman/hsmauth.py
ckman/logging.py
ckman/logging_setup.py
ckman/oath.py
ckman/openpgp.py
ckman/otp.py
ckman/pcsc/__init__.py
ckman/piv.py
ckman/py.typed
ckman/scancodes/__init__.py
ckman/scancodes/bepo.py
ckman/scancodes/de.py
ckman/scancodes/fr.py
ckman/scancodes/it.py
ckman/scancodes/modhex.py
ckman/scancodes/norman.py
ckman/scancodes/uk.py
ckman/scancodes/us.py
ckman/scripting.py
ckman/settings.py
ckman/util.py
canokey_manager-5.4.0.post1.dist-info/COPYING
canokey_manager-5.4.0.post1.dist-info/METADATA
canokey_manager-5.4.0.post1.dist-info/WHEEL
canokey_manager-5.4.0.post1.dist-info/entry_points.txt
canokey_manager-5.4.0.post1.dist-info/RECORD
